pyartifactsmmo/__init__.py
pyartifactsmmo/api_client.py
pyartifactsmmo/api_response.py
pyartifactsmmo/configuration.py
pyartifactsmmo/exceptions.py
pyartifactsmmo/py.typed
pyartifactsmmo/rest.py
pyartifactsmmo/api/__init__.py
pyartifactsmmo/api/accounts_api.py
pyartifactsmmo/api/characters_api.py
pyartifactsmmo/api/default_api.py
pyartifactsmmo/api/events_api.py
pyartifactsmmo/api/grand_exchange_api.py
pyartifactsmmo/api/items_api.py
pyartifactsmmo/api/maps_api.py
pyartifactsmmo/api/monsters_api.py
pyartifactsmmo/api/my_account_api.py
pyartifactsmmo/api/my_characters_api.py
pyartifactsmmo/api/resources_api.py
pyartifactsmmo/api/token_api.py
pyartifactsmmo/models/__init__.py
pyartifactsmmo/models/action_item_bank_response_schema.py
pyartifactsmmo/models/active_event_schema.py
pyartifactsmmo/models/add_account_schema.py
pyartifactsmmo/models/add_character_schema.py
pyartifactsmmo/models/announcement_schema.py
pyartifactsmmo/models/bank_item_schema.py
pyartifactsmmo/models/blocked_hits_schema.py
pyartifactsmmo/models/change_password.py
pyartifactsmmo/models/character_fight_data_schema.py
pyartifactsmmo/models/character_fight_response_schema.py
pyartifactsmmo/models/character_movement_data_schema.py
pyartifactsmmo/models/character_movement_response_schema.py
pyartifactsmmo/models/character_response_schema.py
pyartifactsmmo/models/character_schema.py
pyartifactsmmo/models/cooldown_schema.py
pyartifactsmmo/models/craft_schema.py
pyartifactsmmo/models/crafting_schema.py
pyartifactsmmo/models/data_page_active_event_schema.py
pyartifactsmmo/models/data_page_character_schema.py
pyartifactsmmo/models/data_page_ge_item_schema.py
pyartifactsmmo/models/data_page_item_schema.py
pyartifactsmmo/models/data_page_log_schema.py
pyartifactsmmo/models/data_page_map_schema.py
pyartifactsmmo/models/data_page_monster_schema.py
pyartifactsmmo/models/data_page_resource_schema.py
pyartifactsmmo/models/data_page_simple_item_schema.py
pyartifactsmmo/models/delete_character_schema.py
pyartifactsmmo-1.0.1.dist-info/METADATA
pyartifactsmmo-1.0.1.dist-info/WHEEL
pyartifactsmmo-1.0.1.dist-info/top_level.txt
pyartifactsmmo-1.0.1.dist-info/RECORD
