Metadata-Version: 2.1
Name: pyartifactsmmo
Version: 1.0.1
Summary: Artifacts API
Home-page: 
Author: OpenAPI Generator community
Author-email: team@openapitools.org
Keywords: OpenAPI,OpenAPI-Generator,Artifacts API
Requires-Dist: urllib3 <2.1.0,>=1.25.3
Requires-Dist: python-dateutil
Requires-Dist: aiohttp >=3.0.0
Requires-Dist: aiohttp-retry >=2.8.3
Requires-Dist: pydantic >=2
Requires-Dist: typing-extensions >=4.7.1
